thrivescraper/__init__.py
thrivescraper/_version.py
thrivescraper/github.py
thrivescraper/py.typed
thrivescraper/thrivescraper.py
thrivescraper/tests/__init__.py
thrivescraper/tests/test_thrivescraper.py
thrivescraper-1.0.dist-info/LICENSE
thrivescraper-1.0.dist-info/METADATA
thrivescraper-1.0.dist-info/WHEEL
thrivescraper-1.0.dist-info/entry_points.txt
thrivescraper-1.0.dist-info/top_level.txt
thrivescraper-1.0.dist-info/RECORD
