Metadata-Version: 2.1
Name: thrivescraper
Version: 1.0
Summary: A web scraper for the THRIVE project
Author-email: Paul Saxe <psaxe@vt.edu>
License: BSD-3-Clause
Project-URL: Source, https://github.com/csmol/thrivescraper/
Classifier: Development Status :: 3 - Alpha
Classifier: License :: OSI Approved :: BSD License
Classifier: Natural Language :: English
Classifier: Operating System :: OS Independent
Classifier: Programming Language :: Python :: 3
Classifier: Topic :: Software Development
Requires-Python: >=3.11
License-File: LICENSE
Requires-Dist: beautifulsoup4
Requires-Dist: pygithub
Requires-Dist: requests
Provides-Extra: test
Requires-Dist: pytest >=6.1.2 ; extra == 'test'
Requires-Dist: pytest-runner ; extra == 'test'
